sphinx_plotly_directive/__init__.py
sphinx_plotly_directive/utils.py
sphinx_plotly_directive/version.py
sphinx_plotly_directive-0.1.3.dist-info/LICENSE
sphinx_plotly_directive-0.1.3.dist-info/METADATA
sphinx_plotly_directive-0.1.3.dist-info/WHEEL
sphinx_plotly_directive-0.1.3.dist-info/top_level.txt
sphinx_plotly_directive-0.1.3.dist-info/RECORD
