Metadata-Version: 2.1
Name: sphinx-plotly-directive
Version: 0.1.3
Summary: A directive for including a plotly figure in a Sphinx document
Home-page: https://github.com/harupy/sphinx-plotly-directive
Maintainer: harupy
Maintainer-email: hkawamura0130@gmail.com
License: UNKNOWN
Platform: UNKNOWN
Requires-Python: >=3.6
Provides-Extra: dev
